Ackbar-0.2.data/scripts/ackbar.py
ackbar_lib/B2_recommended_thresholds.py
ackbar_lib/__init__.py
ackbar_lib/build_pydata.py
ackbar_lib/fileio.py
ackbar_lib/pydata.cpython-38-darwin.so
ackbar_lib/rasters.py
ackbar_lib/shapes.py
test/__init__.py
test/test.py
Ackbar-0.2.dist-info/LICENSE.md
Ackbar-0.2.dist-info/METADATA
Ackbar-0.2.dist-info/WHEEL
Ackbar-0.2.dist-info/top_level.txt
Ackbar-0.2.dist-info/RECORD
