Metadata-Version: 2.1
Name: Ackbar
Version: 0.2
Summary: A Python program to assess Key Biodiversity Areas (KBA) delimitation.
Home-page: https://github.com/nrsalinas/ackbar
Author: Nelson R. Salinas
Author-email: nsalinas@humboldt.org.co
License: GNU GPL v. 3
Keywords: biology conservation biodiversity
Platform: UNKNOWN
Classifier: Topic :: Scientific/Engineering :: Bio-Informatics
Classifier: Topic :: Scientific/Engineering :: GIS
Classifier: Intended Audience :: Science/Research
Classifier: License :: OSI Approved :: GNU General Public License v3 (GPLv3)
Requires-Python: >=3
Requires-Dist: fiona
Requires-Dist: shapely
Requires-Dist: pyproj
